{
  "wedding": [
    {
      "name": "sss",
      "message": "sss",
      "attendance": "yes",
      "id": 3
    },
    {
      "name": "bedul",
      "message": "ssss",
      "attendance": "yes",
      "id": 4
    },
    {
      "name": "Dimas Ramdan",
      "message": "cn cnc ",
      "attendance": "yes",
      "id": 5
    },
    {
      "name": "Front End Java Script Wave 5",
      "message": "dddd",
      "attendance": "no",
      "id": 6
    },
    {
      "name": "DDD",
      "message": "SDS",
      "attendance": "yes",
      "id": 7
    },
    {
      "name": "sss",
      "message": "ssss",
      "attendance": "yes",
      "id": 8
    },
    {
      "name": "ssdfdeqwe",
      "message": "qee",
      "attendance": "no",
      "id": 9
    },
    {
      "name": "xxx",
      "message": "unsufbvf",
      "attendance": "no",
      "id": 10
    },
    {
      "name": "Risna ana",
      "message": "sss",
      "attendance": "yes",
      "id": 11
    },
    {
      "name": "Risna ana",
      "message": "sss",
      "attendance": "yes",
      "id": 12
    },
    {
      "name": "Risna ana",
      "message": "sss",
      "attendance": "yes",
      "id": 13
    },
    {
      "name": "Risna ana",
      "message": "sss",
      "attendance": "yes",
      "id": 14
    },
    {
      "name": "Risna ana",
      "message": "sss",
      "attendance": "yes",
      "id": 15
    },
    {
      "name": "Risna ana",
      "message": "sss",
      "attendance": "yes",
      "id": 16
    },
    {
      "name": "Risna ana",
      "message": "sss",
      "attendance": "yes",
      "id": 17
    },
    {
      "name": "GARU",
      "message": "SJBSJB",
      "attendance": "yes",
      "id": 18
    }
  ]
}